collective.superfish-2.1-py3.8-nspkg.pth
collective/superfish/__init__.py
collective/superfish/configure.zcml
collective/superfish/interfaces.py
collective/superfish/tests.py
collective/superfish/browser/__init__.py
collective/superfish/browser/configure.zcml
collective/superfish/browser/interfaces.py
collective/superfish/browser/sections.pt
collective/superfish/browser/sections.py
collective/superfish/browser/static/bundle-superfish-compiled.js
collective/superfish/browser/static/bundle.js
collective/superfish/browser/static/hoverIntent.js
collective/superfish/browser/static/pattern.js
collective/superfish/browser/static/pattern.less
collective/superfish/browser/static/superfish-compiled.js
collective/superfish/browser/static/superfish-hoverIntent-compiled.js
collective/superfish/browser/static/superfish-pattern-compiled.js
collective/superfish/browser/static/superfish.js
collective/superfish/browser/static/superfish.less
collective/superfish/browser/static/superfish.min.css
collective/superfish/browser/static/superfish.min.css.map
collective/superfish/browser/static/superfish.min.js
collective/superfish/browser/static/superfish.min.js.map
collective/superfish/profiles/default/browserlayer.xml
collective/superfish/profiles/default/metadata.xml
collective/superfish/profiles/default/registry.xml
collective/superfish/profiles/default/viewlets.xml
collective/superfish/profiles/uninstall/browserlayer.xml
collective/superfish/profiles/uninstall/registry.xml
collective/superfish/profiles/uninstall/viewlets.xml
collective/superfish/upgrades/__init__.py
collective/superfish/upgrades/configure.zcml
collective/superfish/upgrades/profiles.zcml
collective/superfish/upgrades/profiles/1_to_2/cssregistry.xml
collective/superfish/upgrades/profiles/2_to_5/cssregistry.xml
collective/superfish/upgrades/profiles/2_to_5/jsregistry.xml
collective/superfish/upgrades/profiles/2_to_5/registry.xml
collective.superfish-2.1.dist-info/METADATA
collective.superfish-2.1.dist-info/WHEEL
collective.superfish-2.1.dist-info/entry_points.txt
collective.superfish-2.1.dist-info/namespace_packages.txt
collective.superfish-2.1.dist-info/top_level.txt
collective.superfish-2.1.dist-info/RECORD
