Metadata-Version: 2.1
Name: collective.superfish
Version: 2.1
Summary: A suckerfish/superfish integration into plone
Home-page: https://github.com/collective/collective.superfish
Author: Peter Mathis
Author-email: peter.mathis@kombinat.at
License: GPL
Keywords: navigation suckerfish superfish jquery dropdown
Classifier: Development Status :: 5 - Production/Stable
Classifier: Environment :: Web Environment
Classifier: Framework :: Plone
Classifier: Framework :: Plone :: 5.0
Classifier: Framework :: Plone :: 5.1
Classifier: Framework :: Plone :: 5.2
Classifier: Framework :: Plone :: Addon
Classifier: License :: OSI Approved :: GNU General Public License v2 (GPLv2)
Classifier: Programming Language :: Python
Classifier: Programming Language :: Python :: 2.7
Classifier: Programming Language :: Python :: 3.6
Classifier: Programming Language :: Python :: 3.7
Classifier: Programming Language :: Python :: 3.8
Requires-Dist: setuptools
